{
    "CompileStrategy": "fullobj",
    "MlibObjs": {},
    "CompileStatus": "Successful",
    "PrevCompiledModules": {
        "...MASTER...": {
            "amcQw_d": {
                "mod": "...MASTER...",
                "bytes": 4499,
                "mode": 4,
                "checksum": 0,
                "out": "objs/amcQw_d.o"
            }
        },
        "sh_reg_test": {
            "hVvst_d": {
                "mod": "sh_reg_test",
                "bytes": 4492,
                "mode": 4,
                "archive": "archive.2/_5994_archive_1.a",
                "checksum": 0,
                "out": "hVvst_d.o"
            }
        }
    },
    "CurCompileModules": [
        "...MASTER...",
        "...MASTER...",
        "sh_reg_test",
        "sh_reg_test"
    ],
    "NameTable": {
        "sh_reg_test": [
            "sh_reg_test",
            "hVvst",
            "module"
        ],
        "...MASTER...": [
            "SIM",
            "amcQw",
            "module"
        ]
    },
    "CurCompileUdps": {},
    "PEModules": [],
    "stat": {
        "ru_self_cgstart": {
            "ru_minflt": 4236,
            "ru_utime_sec": 0.065747,
            "ru_stime_sec": 0.080920000000000006,
            "ru_majflt": 665,
            "ru_maxrss_kb": 79448,
            "ru_nvcsw": 699,
            "ru_nivcsw": 3
        },
        "ru_childs_cgstart": {
            "ru_minflt": 0,
            "ru_utime_sec": 0.0,
            "ru_stime_sec": 0.0,
            "ru_majflt": 0,
            "ru_maxrss_kb": 0,
            "ru_nvcsw": 0,
            "ru_nivcsw": 0
        },
        "ru_childs_end": {
            "ru_minflt": 213,
            "ru_utime_sec": 0.0050130000000000001,
            "ru_stime_sec": 0.0,
            "ru_majflt": 0,
            "ru_maxrss_kb": 14368,
            "ru_nvcsw": 1,
            "ru_nivcsw": 0
        },
        "Frontend(%)": 80.201763909389229,
        "outputSizePerQuad": 5077.0,
        "nMops": 13,
        "nQuads": 14,
        "totalObjSize": 71078,
        "ru_self_end": {
            "ru_minflt": 5748,
            "ru_utime_sec": 0.081976999999999994,
            "ru_stime_sec": 0.087099999999999997,
            "ru_majflt": 696,
            "ru_maxrss_kb": 86252,
            "ru_nvcsw": 733,
            "ru_nivcsw": 3
        },
        "mopSpeed": 800.98582871226154,
        "quadSpeed": 862.60012322858938,
        "mop/quad": 0.9285714285714286,
        "CodeGen(%)": 19.798236090610775
    },
    "SIMBData": {
        "out": "amcQwB.o",
        "bytes": 56652
    },
    "LVLData": [
        "SIM"
    ],
    "CompileProcesses": [
        "cgproc.5994.json"
    ],
    "Misc": {
        "default_output_dir": "csrc",
        "daidir": "simv.daidir",
        "csrc": "csrc",
        "cwd": "/home/fmrt/workspace/branch_predictor/branch_predictor/sim",
        "csrc_abs": "/home/fmrt/workspace/branch_predictor/branch_predictor/sim/csrc",
        "daidir_abs": "/home/fmrt/workspace/branch_predictor/branch_predictor/sim/simv.daidir",
        "archive_dir": "archive.2"
    }
}